hpgeom-1.4.0.dist-info/zip-safe
hpgeom-1.4.0.dist-info/RECORD
hpgeom-1.4.0.dist-info/LICENSE
hpgeom-1.4.0.dist-info/WHEEL
hpgeom-1.4.0.dist-info/top_level.txt
hpgeom-1.4.0.dist-info/METADATA
hpgeom/healpy_compat.py
hpgeom/__init__.py
hpgeom/_hpgeom.cpython-310-darwin.so
hpgeom/hpgeom.py
