Metadata-Version: 2.1
Name: hpgeom
Version: 1.4.0
Summary: HEALPix pixel lookup and geometry routines with numpy
Home-page: https://github.com/lsstdesc/hpgeom
Author: Eli Rykoff, Dark Energy Science Collaboration
Author-email: erykoff@stanford.edu
Classifier: Intended Audience :: Science/Research
Classifier: License :: OSI Approved :: GNU General Public License v3 or later (GPLv3+)
Classifier: Operating System :: POSIX :: Linux
Classifier: Operating System :: MacOS
Classifier: Operating System :: Microsoft :: Windows
Classifier: Programming Language :: C
Classifier: Programming Language :: Python :: 3
Classifier: Programming Language :: Python :: 3.7
Classifier: Programming Language :: Python :: 3.8
Classifier: Programming Language :: Python :: 3.9
Classifier: Programming Language :: Python :: 3.10
Requires-Python: >=3.7
License-File: LICENSE
Requires-Dist: numpy
Provides-Extra: test
Requires-Dist: pytest; extra == "test"
Requires-Dist: flake8; extra == "test"
Provides-Extra: test-with-healpy
Requires-Dist: healpy>=1.17; extra == "test-with-healpy"
